lightweightdocumentengine/__init__.py
lightweightdocumentengine-0.0.0.dist-info/WHEEL
lightweightdocumentengine-0.0.0.dist-info/METADATA
lightweightdocumentengine-0.0.0.dist-info/RECORD
