Metadata-Version: 2.1
Name: lightweightdocumentengine
Version: 0.0.0
Summary: A Lightweight Document Engine
Author: Dan Sikes
Author-email: dansikes7@gmail.com
Requires-Python: >=3.9,<4.0
Classifier: Programming Language :: Python :: 3
Classifier: Programming Language :: Python :: 3.10
Classifier: Programming Language :: Python :: 3.9
